cmod
