Metadata-Version: 1.0
Name: cmod
Version: 0.0.6
Summary: Cmake package retrieval
Home-page: https://github.com/gottingen/cmod
Author: Paul Fultz II
Author-email: pfultz2@yahoo.com
License: bsd
Platform: UNKNOWN
